.gitignore
README.txt
bootstrap.py
buildout.cfg
setup.py
collective/__init__.py
collective.recipe.celery.egg-info/PKG-INFO
collective.recipe.celery.egg-info/SOURCES.txt
collective.recipe.celery.egg-info/dependency_links.txt
collective.recipe.celery.egg-info/entry_points.txt
collective.recipe.celery.egg-info/namespace_packages.txt
collective.recipe.celery.egg-info/not-zip-safe
collective.recipe.celery.egg-info/requires.txt
collective.recipe.celery.egg-info/top_level.txt
collective/recipe/__init__.py
collective/recipe/celery/README.txt
collective/recipe/celery/__init__.py
collective/recipe/celery/options.py
collective/recipe/celery/tests.py
docs/HISTORY.txt
docs/LICENSE.GPL
docs/LICENSE.txt