Metadata-Version: 1.0
Name: collective.recipe.celery
Version: 1.0
Summary: A buildout recipe to install and configure Celery
Home-page: https://github.com/collective/collective.recipe.celery
Author: Thomas Buchberger
Author-email: t.buchberger@4teamwork.ch
License: GPL
Platform: UNKNOWN
Classifier: Framework :: Buildout :: Recipe
Classifier: Intended Audience :: Developers
Classifier: License :: OSI Approved :: GNU General Public License (GPL)
Classifier: Programming Language :: Python
Classifier: Topic :: Software Development :: Build Tools
Classifier: Topic :: Software Development :: Libraries :: Python Modules
